pikepdf/__init__.py
pikepdf/_augments.py
pikepdf/_core.cpython-311-aarch64-linux-musl.so
pikepdf/_core.pyi
pikepdf/_cpphelpers.py
pikepdf/_data.py
pikepdf/_exceptions.py
pikepdf/_explicit_conv.py
pikepdf/_io.py
pikepdf/_methods.py
pikepdf/_version.py
pikepdf/_xml.py
pikepdf/canvas.py
pikepdf/codec.py
pikepdf/exceptions.py
pikepdf/form.py
pikepdf/jbig2.py
pikepdf/objects.py
pikepdf/py.typed
pikepdf/settings.py
pikepdf/models/__init__.py
pikepdf/models/_content_stream.py
pikepdf/models/_transcoding.py
pikepdf/models/ctm.py
pikepdf/models/encryption.py
pikepdf/models/image.py
pikepdf/models/outlines.py
pikepdf/models/metadata/__init__.py
pikepdf/models/metadata/_constants.py
pikepdf/models/metadata/_converters.py
pikepdf/models/metadata/_core.py
pikepdf/models/metadata/_docinfo.py
pikepdf/models/metadata/_xmp.py
pikepdf.libs/libgcc_s-2d945d6c.so.1
pikepdf.libs/libjpeg-0de9069a.so.8.3.2
pikepdf.libs/libqpdf-fcbc52fa.so.30.2.0
pikepdf.libs/libstdc++-85f2cd6d.so.6.0.33
pikepdf-10.2.0.dist-info/METADATA
pikepdf-10.2.0.dist-info/WHEEL
pikepdf-10.2.0.dist-info/top_level.txt
pikepdf-10.2.0.dist-info/RECORD
pikepdf-10.2.0.dist-info/licenses/LICENSE.txt
